[
  {
    "day": "2026_07_04",
    "index": 13,
    "topic": "Recursion_and_Backtracking",
    "question": "Palindrome Partitioning"
  },
  {
    "day": "2026_07_04",
    "index": 14,
    "topic": "Dynamic_Programming",
    "question": "Longest Increasing Subsequence"
  },
  {
    "day": "2026_07_04",
    "index": 15,
    "topic": "Arrays_and_Strings",
    "question": "Contains Duplicate"
  },
  {
    "day": "2026_07_04",
    "index": 16,
    "topic": "Dynamic_Programming",
    "question": "Target Sum"
  },
  {
    "day": "2026_07_04",
    "index": 17,
    "topic": "Heaps_and_Priority_Queues",
    "question": "Reorganize String"
  },
  {
    "day": "2026_07_04",
    "index": 18,
    "topic": "Trees_and_Graphs",
    "question": "Redundant Connection"
  },
  {
    "day": "2026_07_04",
    "index": 19,
    "topic": "Dynamic_Programming",
    "question": "Regular Expression Matching"
  },
  {
    "day": "2026_07_04",
    "index": 20,
    "topic": "Recursion_and_Backtracking",
    "question": "Letter Combinations of Phone Number"
  }
]